saasbuild/__init__.py
saasbuild/__main__.py
saasbuild/constants.py
saasbuild/generator.py
saasbuild/assets/activity-helloworld.svg
saasbuild/bundle/__init__.py
saasbuild/bundle/bundle.py
saasbuild/data/flatpak.json
saasbuild/lib/__init__.py
saasbuild/lib/filemgmt.py
saasbuild/lib/process.py
saasbuild/lib/termcolors.py
saasbuild/lib/utils.py
saasbuild/lib/progressbar/__about__.py
saasbuild/lib/progressbar/__init__.py
saasbuild/lib/progressbar/bar.py
saasbuild/lib/progressbar/base.py
saasbuild/lib/progressbar/shortcuts.py
saasbuild/lib/progressbar/utils.py
saasbuild/lib/progressbar/widgets.py
saasbuild/platform/__init__.py
sugarstore_generator/__init__.py
sugarstore_generator/__main__.py
sugarstore_generator/constants.py
sugarstore_generator/generator.py
sugarstore_generator/assets/activity-helloworld.svg
sugarstore_generator/bundle/__init__.py
sugarstore_generator/bundle/bundle.py
sugarstore_generator/data/flatpak.json
sugarstore_generator/lib/__init__.py
sugarstore_generator/lib/filemgmt.py
sugarstore_generator/lib/process.py
sugarstore_generator/lib/termcolors.py
sugarstore_generator/lib/utils.py
sugarstore_generator/lib/progressbar/__about__.py
sugarstore_generator/lib/progressbar/__init__.py
sugarstore_generator/lib/progressbar/bar.py
sugarstore_generator/lib/progressbar/base.py
sugarstore_generator/lib/progressbar/shortcuts.py
sugarstore_generator/lib/progressbar/utils.py
sugarstore_generator/lib/progressbar/widgets.py
sugarstore_generator/platform/__init__.py
sugarstore_generator-0.1a1.dist-info/COPYING
sugarstore_generator-0.1a1.dist-info/LICENSE
sugarstore_generator-0.1a1.dist-info/METADATA
sugarstore_generator-0.1a1.dist-info/WHEEL
sugarstore_generator-0.1a1.dist-info/entry_points.txt
sugarstore_generator-0.1a1.dist-info/top_level.txt
sugarstore_generator-0.1a1.dist-info/RECORD
